hgnested/__init__.py
hgnested-0.8.dist-info/DESCRIPTION.rst
hgnested-0.8.dist-info/METADATA
hgnested-0.8.dist-info/RECORD
hgnested-0.8.dist-info/WHEEL
hgnested-0.8.dist-info/metadata.json
hgnested-0.8.dist-info/top_level.txt
