Metadata-Version: 2.0
Name: hgnested
Version: 0.8
Summary: Mercurial extension to work with nested repositories
Home-page: http://bitbucket.org/cedk/hgnested
Author: B2CK
Author-email: info@b2ck.com
License: GPL-3
Download-URL: http://bitbucket.org/cedk/hgnested/downloads
Platform: UNKNOWN
Classifier: Development Status :: 5 - Production/Stable
Classifier: Environment :: Plugins
Classifier: Intended Audience :: Developers
Classifier: License :: OSI Approved :: GNU General Public License (GPL)
Classifier: Operating System :: OS Independent
Classifier: Programming Language :: Python
Classifier: Topic :: Software Development :: Version Control
Requires-Dist: Mercurial (>=3.6.0)
